setup.py
tigran_test2/__init__.py
tigran_test2.egg-info/PKG-INFO
tigran_test2.egg-info/SOURCES.txt
tigran_test2.egg-info/dependency_links.txt
tigran_test2.egg-info/requires.txt
tigran_test2.egg-info/top_level.txt